iVerilog tutorial/alu.v
module alu(A,B,ALUOp,C);
    input [31:0] A,B;
    input [2:0] ALUOp;
    reg signed [31:0] ta,tb;
    output reg [31:0] C;
    always @(A or B or ALUOp) begin
        case (ALUOp)
            3'b000: C <= A + B;
            3'b001: C <= A - B;
            3'b010: C <= A & B;
            3'b011: C <= A | B;
            3'b100: C <= A >> B;
            3'b101: C <= $signed(A) >>> B;
            3'b110:
                if(A > B) C <= 1;
                else C <= 0;
            3'b111:
                if($signed(A) > $signed(B)) C <= 1;
                else C <= 0;
        endcase
    end
endmodule

iVerilog tutorial/tb.v
`timescale 1ms/1ms
// testbench for simulation
module tb();

    reg [31:0] A,B;
    wire [31:0] C;
    reg [2:0] ALUOp;
    reg [10:0] cnt;
    // instantiation of ALU
    alu U_ALU(.A(A),.B(B),.ALUOp(ALUOp),.C(C));

    initial begin
        $dumpfile("test.vcd");// 指定生成的 vcd 文件名称
        $dumpvars;// 默认记录所有信号到 vcd 文件中
        $display("TEST");
        A=32'h00000003;
        B=32'h00000002;
        ALUOp=3'b000;
        cnt=10'b0;
        #(100) $finish;// 设置仿真停止时间
    end
    always begin
        #(5) ALUOp^=3'b001; 
        cnt+=1;
    end //end always

endmodule

iVerilog tutorial/test.vcd
$date
	Wed Mar  4 10:29:06 2026
$end
$version
	Icarus Verilog
$end
$timescale
	1ms
$end
$scope module tb $end
$var wire 32 ! C [31:0] $end
$var reg 32 " A [31:0] $end
$var reg 3 # ALUOp [2:0] $end
$var reg 32 $ B [31:0] $end
$var reg 11 % cnt [10:0] $end
$scope module U_ALU $end
$var wire 32 & A [31:0] $end
$var wire 3 ' ALUOp [2:0] $end
$var wire 32 ( B [31:0] $end
$var reg 32 ) C [31:0] $end
$upscope $end
$upscope $end
$enddefinitions $end
$comment Show the parameter values. $end
$dumpall
$end
#0
$dumpvars
b101 )
b10 (
b0 '
b11 &
b0 %
b10 $
b0 #
b11 "
b101 !
$end
#5
b1 !
b1 )
b1 %
b1 #
b1 '
#10
b101 !
b101 )
b10 %
b0 #
b0 '
#15
b1 !
b1 )
b11 %
b1 #
b1 '
#20
b101 !
b101 )
b100 %
b0 #
b0 '
#25
b1 !
b1 )
b101 %
b1 #
b1 '
#30
b101 !
b101 )
b110 %
b0 #
b0 '
#35
b1 !
b1 )
b111 %
b1 #
b1 '
#40
b101 !
b101 )
b1000 %
b0 #
b0 '
#45
b1 !
b1 )
b1001 %
b1 #
b1 '
#50
b101 !
b101 )
b1010 %
b0 #
b0 '
#55
b1 !
b1 )
b1011 %
b1 #
b1 '
#60
b101 !
b101 )
b1100 %
b0 #
b0 '
#65
b1 !
b1 )
b1101 %
b1 #
b1 '
#70
b101 !
b101 )
b1110 %
b0 #
b0 '
#75
b1 !
b1 )
b1111 %
b1 #
b1 '
#80
b101 !
b101 )
b10000 %
b0 #
b0 '
#85
b1 !
b1 )
b10001 %
b1 #
b1 '
#90
b101 !
b101 )
b10010 %
b0 #
b0 '
#95
b1 !
b1 )
b10011 %
b1 #
b1 '
#100
b101 !
b101 )
b10100 %
b0 #
b0 '
